py4d_browser_plugin/transform/__init__.py
py4d_browser_plugin/transform/transform.py
py4d_browser_transform-0.0.1.dist-info/licenses/LICENSE.txt
py4d_browser_transform-0.0.1.dist-info/METADATA
py4d_browser_transform-0.0.1.dist-info/WHEEL
py4d_browser_transform-0.0.1.dist-info/top_level.txt
py4d_browser_transform-0.0.1.dist-info/RECORD
