Metadata-Version: 2.4
Name: py4D-browser-transform
Version: 0.0.1
Summary: py4D-browser plugin that adds utility functions which transform the datacube
Author-email: Chia-Hao Lee <chia-hao.lee@cornell.edu>
Project-URL: Homepage, https://github.com/chiahao3/py4D-browser-transform
Project-URL: Repository, https://github.com/chiahao3/py4D-browser-transform
Project-URL: Bug Tracker, https://github.com/chiahao3/py4D-browser-transform/issues
Project-URL: Changelog, https://github.com/chiahao3/py4D-browser-transform/blob/main/CHANGELOG.md
Classifier: Programming Language :: Python :: 3
Classifier: Operating System :: OS Independent
Requires-Python: >=3.10
License-File: LICENSE.txt
Requires-Dist: py4d-browser
Requires-Dist: py4dstem>=0.14.9
Requires-Dist: numpy>=1.19
Dynamic: license-file
